pquality/PartitionQuality.py
pquality/__init__.py
pquality-0.0.9.dist-info/LICENSE
pquality-0.0.9.dist-info/METADATA
pquality-0.0.9.dist-info/WHEEL
pquality-0.0.9.dist-info/top_level.txt
pquality-0.0.9.dist-info/RECORD
