Metadata-Version: 2.1
Name: pquality
Version: 0.0.9
Summary: Community Discovery Partition Quality Indicators
Home-page: https://github.com/GiulioRossetti/partition_quality
Author: Giulio Rossetti
Author-email: giulio.rossetti@gmail.com
License: BSD-2-Clause
Keywords: complex-networks,community-discovery,quality-measures
Platform: UNKNOWN
Classifier: Development Status :: 5 - Production/Stable
Classifier: Intended Audience :: Developers
Classifier: Topic :: Software Development :: Build Tools
Classifier: License :: OSI Approved :: BSD License
Classifier: Operating System :: OS Independent
Classifier: Programming Language :: Python :: 3
Requires-Dist: networkx
Requires-Dist: pandas
Requires-Dist: numpy
